Registration/__init__.py
Registration/envs/Komolenv.py
Registration/envs/__init__.py
Komol-0.0.1.dist-info/METADATA
Komol-0.0.1.dist-info/WHEEL
Komol-0.0.1.dist-info/top_level.txt
Komol-0.0.1.dist-info/RECORD
