Metadata-Version: 2.1
Name: Komol
Version: 0.0.1
Summary: A OpenAI Gym Env for foo
Requires-Dist: gym
